scikit_play-0.1.2.dist-info/licenses/LICENSE
skplay/__init__.py
skplay/estimators.py
skplay/formula.py
skplay/transformer_functions.py
scikit_play-0.1.2.dist-info/METADATA
scikit_play-0.1.2.dist-info/WHEEL
scikit_play-0.1.2.dist-info/top_level.txt
scikit_play-0.1.2.dist-info/RECORD
