Metadata-Version: 2.4
Name: scikit-play
Version: 0.1.2
Summary: Rethinking machine learning pipelines a bit.
Author: Vincent D. Warmerdam
License: MIT License
Project-URL: repository, https://github.com/koaning/scikit-play
Project-URL: issue-tracker, https://github.com/koaning/scikit-play/issues
Project-URL: documentation, https://koaning.github.io/scikit-play/
Classifier: Programming Language :: Python :: 3
Classifier: Programming Language :: Python :: 3.10
Classifier: Programming Language :: Python :: 3.11
Classifier: Programming Language :: Python :: 3.12
Classifier: License :: OSI Approved :: MIT License
Classifier: Topic :: Scientific/Engineering
Classifier: Topic :: Scientific/Engineering :: Artificial Intelligence
Classifier: Topic :: Software Development :: Libraries :: Python Modules
License-File: LICENSE
Requires-Dist: scikit-learn>=1.0
Requires-Dist: narwhals>=0.8.14
Requires-Dist: skrub
Requires-Dist: polars
Requires-Dist: importlib-metadata>=1.0; python_version < "3.8"
Requires-Dist: importlib-resources; python_version < "3.9"
Provides-Extra: lint
Requires-Dist: pre-commit; extra == "lint"
Provides-Extra: test
Requires-Dist: pytest; extra == "test"
Requires-Dist: pandas; extra == "test"
Provides-Extra: dev
Requires-Dist: marimo; extra == "dev"
Requires-Dist: pre-commit; extra == "dev"
Requires-Dist: pytest; extra == "dev"
Requires-Dist: pandas; extra == "dev"
Dynamic: license-file
